sql-fox/Exceptions.py
sql-fox/__init__.py
sql-fox/core.py
sql-fox/db_init.py
sql-fox/imports.py
sql-fox/settings.py
sql-fox/version.py
sql_fox/Exceptions.py
sql_fox/__init__.py
sql_fox/core.py
sql_fox/db_init.py
sql_fox/imports.py
sql_fox/settings.py
sql_fox-0.1.0.dist-info/LICENSE
sql_fox-0.1.0.dist-info/METADATA
sql_fox-0.1.0.dist-info/WHEEL
sql_fox-0.1.0.dist-info/top_level.txt
sql_fox-0.1.0.dist-info/RECORD
